Workbook

Sheet Resumen Ejecutivo
A1: Resumen ejecutivo · Control de préstamos
A2: Conversión del CSV a un libro de Excel con plantilla visual azul, resumen ejecutivo y hojas auxiliares de seguimiento.
B4: Total prestado | D4: Total interés | F4: Restante por cobrar | H4: Total a recibir
B5: =SUMIFS(DANIELA!B:B,DANIELA!A:A,"<>",DANIELA!A:A,"<>NOMBRE",DANIELA!A:A,"<>Resumen") + SUMIFS(FREILINYER!B:B,FREILINYER!A:A,"<>",FREILINYER!A:A,"<>NOMBRE",FREILINYER!A:A,"<>Resumen") -> 1524 | D5: =(SUM(FREILINYER!D:D) + SUM(DANIELA!D:D)) / 2 -> 703.5 | F5: =(SUM(FREILINYER!F:F) + SUM(DANIELA!F:F)) / 2 -> 0 | H5: =SUMIFS(DANIELA!H:H,DANIELA!A:A,"<>",DANIELA!A:A,"<>NOMBRE",DANIELA!A:A,"<>Resumen") + SUMIFS(FREILINYER!H:H,FREILINYER!A:A,"<>",FREILINYER!A:A,"<>NOMBRE",FREILINYER!A:A,"<>Resumen") -> 2150
B8: Préstamos activos | C8: =COUNTA(DANIELA!A:A)-4 + COUNTA(FREILINYER!A:A)-4 -> 15 | E8: Retrasos | F8: =SUMIFS(DANIELA!G:G,DANIELA!A:A,"<>",DANIELA!A:A,"<>NOMBRE",DANIELA!A:A,"<>Resumen") + SUMIFS(FREILINYER!G:G,FREILINYER!A:A,"<>",FREILINYER!A:A,"<>NOMBRE",FREILINYER!A:A,"<>Resumen") -> 179 | H8: Moneda | I8: DÓLARES BCV
A11: Estado | B11: Cantidad
A12: PENDIENTE | B12: =COUNTIF(FREILINYER!L:L, "PENDIENTE") + COUNTIF(DANIELA!K:K, "PENDIENTE") -> 13
A13: RETRASADO | B13: =SUMIFS(DANIELA!G:G,DANIELA!A:A,"<>",DANIELA!A:A,"<>NOMBRE",DANIELA!A:A,"<>Resumen")+SUMIFS(FREILINYER!G:G,FREILINYER!A:A,"<>",FREILINYER!A:A,"<>NOMBRE",FREILINYER!A:A,"<>Resumen") -> 179

Sheet Resumen por Colaborador
A1: Resumen por colaborador
A2: Concentrado de préstamos administrados por colaborador.
A4: Colaborador | B4: Préstamos | C4: Monto prestado | D4: Total a recibir | E4: Retrasos | F4: Promedio por préstamo
A5: Daniela | B5: =COUNTA(DANIELA!A:A)-4 -> 1 | C5: =SUMIFS(DANIELA!B:B,DANIELA!A:A,"<>",DANIELA!A:A,"<>NOMBRE",DANIELA!A:A,"<>Resumen") -> 10 | D5: =SUMIFS(DANIELA!H:H,DANIELA!A:A,"<>",DANIELA!A:A,"<>NOMBRE",DANIELA!A:A,"<>Resumen") -> 15 | E5: =SUMIFS(DANIELA!G:G,DANIELA!A:A,"<>",DANIELA!A:A,"<>NOMBRE",DANIELA!A:A,"<>Resumen") -> 0 | F5: =IFERROR(B5,0) -> 1
A6: Freilinyer | B6: =COUNTA(FREILINYER!A:A)-4 -> 14 | C6: =SUMIFS(FREILINYER!B:B,FREILINYER!A:A,"<>",FREILINYER!A:A,"<>NOMBRE",FREILINYER!A:A,"<>Resumen") -> 1514 | D6: =SUMIFS(FREILINYER!H:H,FREILINYER!A:A,"<>",FREILINYER!A:A,"<>NOMBRE",FREILINYER!A:A,"<>Resumen") -> 2135 | E6: =SUMIFS(FREILINYER!G:G,FREILINYER!A:A,"<>",FREILINYER!A:A,"<>NOMBRE",FREILINYER!A:A,"<>Resumen") -> 179 | F6: =IFERROR(B6,0) -> 14

Sheet FREILINYER
A1: Control de préstamos
A2: Tabla principal con los datos importados del CSV y resaltado del resumen general.
A4: NOMBRE | B4: CANTIDAD PRESTADA | C4: MONEDA | D4: TOTAL INTERÉS | E4: ADELANTO RECIBIDO | F4: RESTANTE POR COBRAR | G4: RETRASOS | H4: TOTAL A RECIBIR | I4: RECIBIDO | J4: FECHA DE PRÉSTAMO | K4: FECHA DE REEMBOLSO | L4: ESTADO DEL PRÉSTAMO | M4: COLABORADOR
A5: JAVI EJERCITO | B5: 100 | C5: DÓLARES BCV | D5: 50 | H5: 150 | J5: 46096 | K5: 3/31/2026 | L5: PENDIENTE
A6: LIVIA | B6: 60 | C6: DÓLARES BCV | D6: 30 | H6: 90 | J6: 46096 | K6: 46057 | L6: PENDIENTE
A7: MARLON | B7: 40 | C7: DÓLARES BCV | D7: 20 | H7: 60 | J7: 46096 | K7: 46057 | L7: PENDIENTE
A8: Pérez iturriago | B8: 100 | C8: DÓLARES BCV | D8: 50 | H8: 150 | J8: 15/03/2026 | K8: 31/03/2016 | L8: PENDIENTE
A9: AMAYRUS | B9: 50 | C9: DÓLARES BCV | D9: 10 | H9: 60 | J9: 15/03/2026 | K9: 31/03/2026 | L9: PENDIENTE
A10: CAP CASTRO | B10: $ 90,00 | C10: DÓLARES BCV | D10: 45 | H10: 135 | J10: 3/18/2026 | K10: 3/31/2026 | L10: PENDIENTE
A11: MONTEIRO | B11: 80 | C11: DÓLARES BCV | D11: 40 | H11: 120 | J11: 46099 | K11: 46112 | L11: PENDIENTE
A12: DÍAZ | B12: 100 | C12: DÓLARES BCV | D12: 40 | H12: 40 | J12: 46099 | K12: 46112 | L12: PENDIENTE
A13: CAP ARIAS | B13: 75 | C13: DÓLARES BCV | D13: 51 | E13: 0 | H13: 126 | J13: 46099 | K13: 46112 | L13: PENDIENTE
A14: RICHAR | B14: 500 | C14: DÓLARES BCV | D14: 200 | E14: 0 | H14: 700 | J14: 46078 | K14: 3/15/2026 | L14: PENDIENTE
A15: ALIS DUEÑO | B15: 100 | C15: DÓLARES BCV | D15: 50 | H15: 150 | J15: 20/03/2026 | K15: 31/03/2026 | L15: PENDIENTE
A16: ALVARO GIL | B16: 100 | C16: DÓLARES BCV | D16: 75 | H16: 175 | J16: 46052 | K16: 46081 | L16: PENDIENTE
A21: DARLING | B21: 59 | C21: DOLARES BCV | D21: 0 | G21: 59 | H21: 59 | L21: PENDIENTE
A22: RONDON | B22: 150 | C22: DÓLARES BCV | D22: 75 | G22: 120 | H22: 120 | J22: 46049 | K22: 46068 | L22: PENDIENTE
G23: TOTAL RETRASOS | H23: =SUM(H21:H22) -> 179
A25: Resumen | B25: =SUM(B5:B20) -> 1305 | D25: =SUM(D5:D20) -> 661 | E25: =SUM(E5:E24) -> 0 | F25: =SUM(F5:F24) -> 0 | G25: =SUM(G5:G24) -> 179 | H25: =SUM(H5:H20) -> 1956 | M25: =SUM(M4:M24) -> 0
G26: TOTAL | H26: =SUM(H23:H25) -> 2135 | I26: =SUM(I5:I22) -> 0

Sheet HISTORIAL FREILINYER
A1: Control de préstamos
A2: Tabla principal con los datos importados del CSV y resaltado del resumen general.
A4: NOMBRE | B4: CANTIDAD PRESTADA | C4: MONEDA | D4: TOTAL INTERÉS | E4: ADELANTO RECIBIDO | F4: RESTANTE POR COBRAR | G4: RETRASOS | H4: TOTAL A RECIBIR | I4: RECIBIDO | J4: FECHA DE PRÉSTAMO | K4: FECHA DE REEMBOLSO | L4: ESTADO DEL PRÉSTAMO | M4: COLABORADOR
A5: RICHAR | B5: 500 | C5: DÓLARES BCV | D5: 200 | E5: 0 | H5: 700 | J5: 2/25/2026 | K5: 3/15/2026 | L5: PENDIENTE
A6: CAP ARIAS | B6: 50 | C6: DÓLARES BCV | D6: 25 | E6: 0 | H6: 75 | J6: 2/28/2026 | K6: 3/15/2026 | L6: PENDIENTE
A7: MONTEIRO | B7: 80 | C7: DÓLARES BCV | D7: 40 | E7: 0 | H7: 120 | J7: 46083 | K7: 46097 | L7: PENDIENTE
A8: DÍAZ | B8: 100 | C8: DÓLARES BCV | D8: 40 | E8: 90 | F8: 40 | H8: 40 | J8: 46080 | K8: 46096 | L8: PENDIENTE
A9: JAVI EJERCITO | B9: 50 | C9: DÓLARES BCV | D9: 25 | E9: 0 | H9: 75 | J9: 46025 | K9: 3/16/2026 | L9: PENDIENTE
A10: CAP CASTRO | B10: 60 | C10: DÓLARES BCV | D10: 30 | E10: 0 | H10: 90 | J10: 2/28/2026 | K10: 3/15/2026 | L10: PENDIENTE
A11: LIVIA | B11: 100 | C11: DÓLARES BCV | D11: 50 | E11: 90 | F11: 60 | H11: 60 | J11: 46056 | K11: 3/16/2026 | L11: PENDIENTE
A12: CASTAÑEDA | B12: 50 | C12: DÓLARES BCV | D12: 25 | E12: 0 | H12: 75 | J12: 46083 | K12: 3/16/2026 | L12: PENDIENTE
A13: WINI | B13: 50 | C13: DÓLARES BCV | D13: 25 | E13: 0 | H13: 75 | J13: 46083 | K13: 3/16/2026 | L13: PENDIENTE
A14: whitney | B14: 20 | C14: DÓLARES BCV | D14: 10 | E14: 0 | H14: 30 | J14: 46085 | K14: 46097 | L14: PENDIENTE
A16: DARLING | B16: 59 | C16: DOLARES BCV | D16: 0 | G16: 59 | H16: 59 | L16: PENDIENTE
A17: RONDON | B17: 150 | C17: DÓLARES BCV | D17: 75 | G17: 120 | H17: 120 | J17: 46049 | K17: 46068 | L17: PENDIENTE
A18: ALVARO GIL | B18: 100 | C18: DÓLARES BCV | D18: 50 | G18: 150 | H18: 175 | J18: 46052 | K18: 46081 | L18: PENDIENTE
G19: TOTAL RETRASOS | H19: =SUM(H16:H18) -> 354
A21: Resumen | B21: =SUM(B5:B20) -> 1369 | D21: =SUM(D5:D20) -> 595 | E21: =SUM(E5:E20) -> 180 | F21: =SUM(F5:F20) -> 100 | G21: =SUM(G5:G20) -> 329 | H21: =SUM(H5:H14) -> 1340 | M21: =SUM(M4:M20) -> 0
G22: TOTAL | H22: =SUM(H19:H21) -> 1694 | I22: =SUM(I5:I18) -> 0

Sheet DANIELA
A1: Control de préstamos
A2: Tabla principal con los datos importados del CSV y resaltado del resumen general.
A4: NOMBRE | B4: CANTIDAD PRESTADA | C4: MONEDA | D4: TOTAL INTERÉS | E4: ADELANTO RECIBIDO | F4: RESTANTE POR COBRAR | G4: RETRASOS | H4: TOTAL A RECIBIR | I4: FECHA DE PRÉSTAMO | J4: FECHA DE REEMBOLSO | K4: ESTADO DEL PRÉSTAMO | L4: COLABORADOR
A5: SANCHES HEREDIA | B5: 10 | C5: DÓLARES BCV | D5: 5 | E5: 0 | H5: 15 | I5: 46082 | J5: 3/15/2026 | K5: PENDIENTE
A7: Resumen | B7: =SUM(B:B) -> 0 | D7: =SUM(D5:D6) -> 5 | E7: =SUM(E5:E6) -> 0 | F7: =SUM(F5:F6) -> 0 | G7: =SUM(G5:G6) -> 0 | H7: =SUM(H5:H6) -> 15 | L7: =SUM(L5:L6) -> 0

Sheet HISTORIAL DANIELA 
A1: Control de préstamos
A2: Tabla principal con los datos importados del CSV y resaltado del resumen general.
A4: NOMBRE | B4: CANTIDAD PRESTADA | C4: MONEDA | D4: TOTAL INTERÉS | E4: ADELANTO RECIBIDO | F4: RESTANTE POR COBRAR | G4: RETRASOS | H4: TOTAL A RECIBIR | I4: FECHA DE PRÉSTAMO | J4: FECHA DE REEMBOLSO | K4: ESTADO DEL PRÉSTAMO | L4: COLABORADOR
A5: SANCHES HEREDIA | B5: 10 | C5: DÓLARES BCV | D5: 5 | E5: 0 | H5: 15 | I5: 46082 | J5: 3/15/2026 | K5: PENDIENTE
A7: Resumen | B7: =SUM(B:B) -> 0 | D7: =SUM(D5:D6) -> 5 | E7: =SUM(E5:E6) -> 0 | F7: =SUM(F5:F6) -> 0 | G7: =SUM(G5:G6) -> 0 | H7: =SUM(H5:H6) -> 15 | L7: =SUM(L5:L6) -> 0

Sheet SAM
A1: SAM · CARTERASAM · CARTERA
A3: MES | B3: NOMBRE | C3: NOV (30/11) | D3: DIC (31/12) | E3: ENE (31/01) | F3: FEB (28/02) | G3: MAR (31/03) | H3: ABR (30/04) | I3: MAY (31/05) | J3: JUN (30/06) | K3: JUL (31/07) | L3: AGO (31/08) | M3: sep(31/09) | N3: TOTAL PAGADO | O3: PENDIENTE
A4: Noviembre | B4: Daniela Velásquez | C4: PAGO | D4: NO PAGO | E4: PAGO | F4: PAGO | M4: Solvente
A5: Diciembre | B5: Freilinyer Colmenarez | C5: PAGO | D5: PAGO | E5: PAGO | F5: PAGO | M5: Solvente
A6: Enero | B6: Sr Fanny | C6: PAGO | D6: PAGO | E6: PAGO | F6: PAGO | M6: Solvente
A7: Febrero | B7: Sr Edmary | C7: PAGO | D7: PAGO | E7: PAGO | F7: PAGO | M7: Solvente
A8: Marzo | B8: Eliu Martinez | C8: PAGO | D8: PAGO | E8: PAGO | F8: PAGO | M8: Solvente
A9: Abril | B9: Cap Castro | C9: TARDE | D9: PAGO | E9: PAGO | F9: PAGO | M9: Ultimo
A10: Mayo | B10: Julio Vargas | C10: PAGO | D10: PAGO | E10: PAGO | F10: PAGO | M10: Solvente
A11: Junio | B11: Freddy Vargas | C11: PAGO | D11: PAGO | E11: PAGO | F11: PAGO | M11: Solvente
A12: Julio | B12: Darling Rodríguez | C12: PAGO | D12: PAGO | E12: PAGO | F12: PAGO | M12: Solvente
A13: Agosto | B13: Romero Vicuña | C13: PAGO | D13: PAGO | E13: PAGO | F13: PAGO | M13: Solvente

Sheet INGRESOS 10%
A1: INGRESOS 10% / 8% · RESUMEN
A3: ORIGEN | B3: TOTAL PRESTADO | C3: TOTAL INTERESES | D3: TOTAL A RECIBIR | E3: % GESTIÓN | F3: TOTAL GESTIÓN | G3: RESPONSABLE | H3: OBSERVACIÓN

Sheet LISTA NEGRA NO PRESTAR
A1: LISTA NEGRA / NO PRESTAR
A3: NOMBRE APELLIDO | B3: CÉDULA | C3: ESTADO | D3: OBSERVACIÓN
A4: EMERSON SOJO | C4: PENDIENTE CÉDULA
A5: CAP CASTRO | C5: PENDIENTE CÉDULA
A6: RAFAEL STUARD | C6: PENDIENTE CÉDULA
A7: AVILA FERNANDEZ | C7: PENDIENTE CÉDULA
A8: JULIO SEGOVIA | C8: PENDIENTE CÉDULA
A9: SAMARY TERRASA BAR | C9: PENDIENTE CÉDULA
A10: RODRIGUEZ PETIT | C10: PENDIENTE CÉDULA
A11: TAIMAR CABELLO | C11: PENDIENTE CÉDULA
A12: SARACUAL TTE DGCIM | C12: PENDIENTE CÉDULA
A13: BAEZ FRANYER BANGU | C13: PENDIENTE CÉDULA
A14: RUMION CARRION BANGU | C14: PENDIENTE CÉDULA
A15: EZEQUIEL FUENTES BANGU | C15: PENDIENTE CÉDULA
... A18: DUBRASKA Pagoda | C18: PENDIENTE CÉDULA
